setup.py
lenex.egg-info/PKG-INFO
lenex.egg-info/SOURCES.txt
lenex.egg-info/dependency_links.txt
lenex.egg-info/requires.txt
lenex.egg-info/top_level.txt
lenexpy/__init__.py
lenexpy/adapters.py
lenexpy/decoder/__init__.py
lenexpy/decoder/decoder.py
lenexpy/decoder/encoder.py
lenexpy/decoder/lef_decoder.py
lenexpy/decoder/lef_encoder.py
lenexpy/decoder/lxf_decoder.py
lenexpy/decoder/lxf_encoder.py