Metadata-Version: 2.1
Name: lenex
Version: 0.0.1
Summary: LenexPY handler for MEET Entry Editor
